icinga2client/__init__.py
icinga2client/version.py
icinga2client/api/__init__.py
icinga2client/api/authentication.py
icinga2client/api/base.py
icinga2client/api/filters.py
icinga2client/api/methods.py
icinga2client/api/models.py
icinga2client/cli/__init__.py
icinga2client/cli/acknowledge.py
icinga2client/cli/configure.py
icinga2client/cli/downtime.py
icinga2client/config/__init__.py
icinga2client/helpers/__init__.py
icinga2client/helpers/data.py
icinga2client/helpers/interactive.py
icinga2client-0.2.0.dist-info/DESCRIPTION.rst
icinga2client-0.2.0.dist-info/METADATA
icinga2client-0.2.0.dist-info/RECORD
icinga2client-0.2.0.dist-info/WHEEL
icinga2client-0.2.0.dist-info/entry_points.txt
icinga2client-0.2.0.dist-info/metadata.json
icinga2client-0.2.0.dist-info/top_level.txt
