Metadata-Version: 1.1
Name: icinga2client
Version: 0.2.0
Summary: Manage icinga2 from the command-line.
Home-page: https://github.com/lewiseason/icinga2client.git
Author: Lewis Eason
Author-email: me@lewiseason.co.uk
License: UNKNOWN
Platform: UNKNOWN
Classifier: Development Status :: 3 - Alpha
Classifier: Environment :: Console
Classifier: Intended Audience :: System Administrators
Classifier: License :: OSI Approved :: GNU General Public License v3 (GPLv3)
Classifier: Natural Language :: English
Classifier: Programming Language :: Python :: 2.7
Classifier: Programming Language :: Python :: 3
Classifier: Topic :: System :: Monitoring
